Workbook

Sheet Task Plan
A1: HOPE, Inc. ERP - Planned Tasks per Team Member per Sprint
A2: Each task is one planned PR. Enter the member's name, update Status as work progresses (Merged = done), and paste the PR link. Use the filter on row 4 to view one sprint or one role. Light-blue cells were revised to add User Management and Reports (see Change Log).
A4: Task ID | B4: Sprint | C4: Week | D4: Role | E4: Assigned to (name) | F4: Task (one PR) | G4: Due (sprint day) | H4: Status | I4: PR link | J4: Notes
A5: S1-DEV-01 | B5: 1 | C5: 1 | D5: Developer | F5: Project scaffold: app skeleton, env config, DB connection | G5: 2 | H5: Not started
A6: S1-DEV-02 | B6: 1 | C6: 1 | D6: Developer | F6: Register user form and API (new users start as pending) | G6: 4 | H6: Not started
A7: S1-DEV-03 | B7: 1 | C7: 2 | D7: Developer | F7: Login and logout with session handling; password hashing and set-password on first login; blocked users cannot sign in | G7: 6 | H7: Not started
A8: S1-DEV-04 | B8: 1 | C8: 2 | D8: Developer | F8: Reset password: request, emailed token, reset form | G8: 7 | H8: Not started
A9: S1-DEV-05 | B9: 1 | C9: 2 | D9: Developer | F9: User Management screen: user list, Add User, Edit User, Block/Unblock; Admin manages Users only and Superadmin accounts are hidden | G9: 8 | H9: Not started
A10: S1-DEV-06 | B10: 1 | C10: 2 | D10: Developer | F10: Superadmin: approve pending users and designate admins; block removing or disabling the last remaining superadmin | G10: 8 | H10: Not started
A11: S1-DEV-07 | B11: 1 | C11: 2 | D11: Developer | F11: Rights dialog: admin/superadmin assign per-action rights by module (Customer, Product, Human Resources, Sales, Reports) with module checkbox and All/None; log every rights change in audit_log | G11: 9 | H11: Not started
A12: S1-DEV-08 | B12: 1 | C12: 2 | D12: Developer | F12: Main page: sidebar and module tiles by role and rights, plus server-side permission check | G12: 9 | H12: Not started
A13: S1-DBA-01 | B13: 1 | C13: 1 | D13: DB Admin | F13: Team database setup, migration runner script, and student setup README (no Docker) | G13: 2 | H13: Not started
A14: S1-DBA-02 | B14: 1 | C14: 1 | D14: DB Admin | F14: Migration: HOPE base tables and sample data from HopeDB_audit.sql | G14: 3 | H14: Not started
A15: S1-DBA-03 | B15: 1 | C15: 1 | D15: DB Admin | F15: Migration: app_user (role, blocked flag), role, module, rights catalogue, user_permission (with soft delete) | G15: 4 | H15: Not started
A16: S1-DBA-04 | B16: 1 | C16: 1 | D16: DB Admin | F16: Migration: password reset token table (hashed, expiry, used flag) | G16: 5 | H16: Not started
... A124: S4-SM-05 | B124: 4 | C124: 8 | D124: Scrum Master | F124: Final review, retrospective and project report | G124: 10 | H124: Not started

Sheet Summary
A1: Progress Summary (planned vs merged PRs)
A2: Formulas read the Task Plan sheet. 'Merged' = done.
A4: Role | B4: S1 planned | C4: S1 merged | D4: S2 planned | E4: S2 merged | F4: S3 planned | G4: S3 merged | H4: S4 planned | I4: S4 merged | J4: Total planned | K4: Total merged | L4: % done
A5: Developer | B5: =COUNTIFS('Task Plan'!$D$5:$D$124,$A5,'Task Plan'!$B$5:$B$124,1) -> 8 | C5: =COUNTIFS('Task Plan'!$D$5:$D$124,$A5,'Task Plan'!$B$5:$B$124,1,'Task Plan'!$H$5:$H$124,"Merged") -> 0 | D5: =COUNTIFS('Task Plan'!$D$5:$D$124,$A5,'Task Plan'!$B$5:$B$124,2) -> 8 | E5: =COUNTIFS('Task Plan'!$D$5:$D$124,$A5,'Task Plan'!$B$5:$B$124,2,'Task Plan'!$H$5:$H$124,"Merged") -> 0 | F5: =COUNTIFS('Task Plan'!$D$5:$D$124,$A5,'Task Plan'!$B$5:$B$124,3) -> 8 | G5: =COUNTIFS('Task Plan'!$D$5:$D$124,$A5,'Task Plan'!$B$5:$B$124,3,'Task Plan'!$H$5:$H$124,"Merged") -> 0 | H5: =COUNTIFS('Task Plan'!$D$5:$D$124,$A5,'Task Plan'!$B$5:$B$124,4) -> 8 | I5: =COUNTIFS('Task Plan'!$D$5:$D$124,$A5,'Task Plan'!$B$5:$B$124,4,'Task Plan'!$H$5:$H$124,"Merged") -> 0 | J5: =B5+D5+F5+H5 -> 32 | K5: =C5+E5+G5+I5 -> 0 | L5: =IF(J5=0,0,K5/J5) -> 0
A6: DB Admin | B6: =COUNTIFS('Task Plan'!$D$5:$D$124,$A6,'Task Plan'!$B$5:$B$124,1) -> 6 | C6: =COUNTIFS('Task Plan'!$D$5:$D$124,$A6,'Task Plan'!$B$5:$B$124,1,'Task Plan'!$H$5:$H$124,"Merged") -> 0 | D6: =COUNTIFS('Task Plan'!$D$5:$D$124,$A6,'Task Plan'!$B$5:$B$124,2) -> 6 | E6: =COUNTIFS('Task Plan'!$D$5:$D$124,$A6,'Task Plan'!$B$5:$B$124,2,'Task Plan'!$H$5:$H$124,"Merged") -> 0 | F6: =COUNTIFS('Task Plan'!$D$5:$D$124,$A6,'Task Plan'!$B$5:$B$124,3) -> 6 | G6: =COUNTIFS('Task Plan'!$D$5:$D$124,$A6,'Task Plan'!$B$5:$B$124,3,'Task Plan'!$H$5:$H$124,"Merged") -> 0 | H6: =COUNTIFS('Task Plan'!$D$5:$D$124,$A6,'Task Plan'!$B$5:$B$124,4) -> 6 | I6: =COUNTIFS('Task Plan'!$D$5:$D$124,$A6,'Task Plan'!$B$5:$B$124,4,'Task Plan'!$H$5:$H$124,"Merged") -> 0 | J6: =B6+D6+F6+H6 -> 24 | K6: =C6+E6+G6+I6 -> 0 | L6: =IF(J6=0,0,K6/J6) -> 0
A7: Tester | B7: =COUNTIFS('Task Plan'!$D$5:$D$124,$A7,'Task Plan'!$B$5:$B$124,1) -> 6 | C7: =COUNTIFS('Task Plan'!$D$5:$D$124,$A7,'Task Plan'!$B$5:$B$124,1,'Task Plan'!$H$5:$H$124,"Merged") -> 0 | D7: =COUNTIFS('Task Plan'!$D$5:$D$124,$A7,'Task Plan'!$B$5:$B$124,2) -> 6 | E7: =COUNTIFS('Task Plan'!$D$5:$D$124,$A7,'Task Plan'!$B$5:$B$124,2,'Task Plan'!$H$5:$H$124,"Merged") -> 0 | F7: =COUNTIFS('Task Plan'!$D$5:$D$124,$A7,'Task Plan'!$B$5:$B$124,3) -> 6 | G7: =COUNTIFS('Task Plan'!$D$5:$D$124,$A7,'Task Plan'!$B$5:$B$124,3,'Task Plan'!$H$5:$H$124,"Merged") -> 0 | H7: =COUNTIFS('Task Plan'!$D$5:$D$124,$A7,'Task Plan'!$B$5:$B$124,4) -> 6 | I7: =COUNTIFS('Task Plan'!$D$5:$D$124,$A7,'Task Plan'!$B$5:$B$124,4,'Task Plan'!$H$5:$H$124,"Merged") -> 0 | J7: =B7+D7+F7+H7 -> 24 | K7: =C7+E7+G7+I7 -> 0 | L7: =IF(J7=0,0,K7/J7) -> 0
A8: UI/UX Designer | B8: =COUNTIFS('Task Plan'!$D$5:$D$124,$A8,'Task Plan'!$B$5:$B$124,1) -> 5 | C8: =COUNTIFS('Task Plan'!$D$5:$D$124,$A8,'Task Plan'!$B$5:$B$124,1,'Task Plan'!$H$5:$H$124,"Merged") -> 0 | D8: =COUNTIFS('Task Plan'!$D$5:$D$124,$A8,'Task Plan'!$B$5:$B$124,2) -> 5 | E8: =COUNTIFS('Task Plan'!$D$5:$D$124,$A8,'Task Plan'!$B$5:$B$124,2,'Task Plan'!$H$5:$H$124,"Merged") -> 0 | F8: =COUNTIFS('Task Plan'!$D$5:$D$124,$A8,'Task Plan'!$B$5:$B$124,3) -> 5 | G8: =COUNTIFS('Task Plan'!$D$5:$D$124,$A8,'Task Plan'!$B$5:$B$124,3,'Task Plan'!$H$5:$H$124,"Merged") -> 0 | H8: =COUNTIFS('Task Plan'!$D$5:$D$124,$A8,'Task Plan'!$B$5:$B$124,4) -> 5 | I8: =COUNTIFS('Task Plan'!$D$5:$D$124,$A8,'Task Plan'!$B$5:$B$124,4,'Task Plan'!$H$5:$H$124,"Merged") -> 0 | J8: =B8+D8+F8+H8 -> 20 | K8: =C8+E8+G8+I8 -> 0 | L8: =IF(J8=0,0,K8/J8) -> 0
A9: Scrum Master | B9: =COUNTIFS('Task Plan'!$D$5:$D$124,$A9,'Task Plan'!$B$5:$B$124,1) -> 5 | C9: =COUNTIFS('Task Plan'!$D$5:$D$124,$A9,'Task Plan'!$B$5:$B$124,1,'Task Plan'!$H$5:$H$124,"Merged") -> 0 | D9: =COUNTIFS('Task Plan'!$D$5:$D$124,$A9,'Task Plan'!$B$5:$B$124,2) -> 5 | E9: =COUNTIFS('Task Plan'!$D$5:$D$124,$A9,'Task Plan'!$B$5:$B$124,2,'Task Plan'!$H$5:$H$124,"Merged") -> 0 | F9: =COUNTIFS('Task Plan'!$D$5:$D$124,$A9,'Task Plan'!$B$5:$B$124,3) -> 5 | G9: =COUNTIFS('Task Plan'!$D$5:$D$124,$A9,'Task Plan'!$B$5:$B$124,3,'Task Plan'!$H$5:$H$124,"Merged") -> 0 | H9: =COUNTIFS('Task Plan'!$D$5:$D$124,$A9,'Task Plan'!$B$5:$B$124,4) -> 5 | I9: =COUNTIFS('Task Plan'!$D$5:$D$124,$A9,'Task Plan'!$B$5:$B$124,4,'Task Plan'!$H$5:$H$124,"Merged") -> 0 | J9: =B9+D9+F9+H9 -> 20 | K9: =C9+E9+G9+I9 -> 0 | L9: =IF(J9=0,0,K9/J9) -> 0
A10: Team total | B10: =SUM(B5:B9) -> 30 | C10: =SUM(C5:C9) -> 0 | D10: =SUM(D5:D9) -> 30 | E10: =SUM(E5:E9) -> 0 | F10: =SUM(F5:F9) -> 30 | G10: =SUM(G5:G9) -> 0 | H10: =SUM(H5:H9) -> 30 | I10: =SUM(I5:I9) -> 0 | ... K10: =SUM(K5:K9) -> 0 | L10: =IF(J10=0,0,K10/J10) -> 0
A12: Note: planned task counts per sprint (8/6/6/5/5) equal each role's full-score PR target (midterm target; final target = 3 sprints x same count).

Sheet Change Log
A1: Change Log: User Management and Reports added within the same 8 weeks
A2: Fixed limits kept: 4 sprints x 2 weeks = 8 weeks, and the per-role PR targets (8/6/6/5/5 per sprint). New work was fitted in by merging small tasks, not by adding tasks or weeks. Light-blue cells on Task Plan = revised rows.
A3: Check: total tasks | B3: =COUNTA('Task Plan'!A5:A124) -> 120 | C3: Last week used | D3: =MAX('Task Plan'!C5:C124) -> 8 | E3: Revised tasks | F3: =COUNTA(A6:A37) -> 32
A5: Task ID | B5: Role | C5: Sprint | D5: Before | E5: After | F5: Old due day | G5: New due day | H5: Why
A6: S1-DEV-03 | B6: Developer | C6: 1 | D6: Login and logout with session handling | E6: Login and logout with session handling; password hashing and set-password on first login; blocked users cannot sign in | F6: 5 | G6: 6 | H6: Merged old DEV-03 + DEV-04 (login + hashing/set-password) to free one PR slot; blocked-user check added (guide 3.8).
A7: S1-DEV-04 | B7: Developer | C7: 1 | D7: Password hashing and set-password on first login | E7: Reset password: request, emailed token, reset form | F7: 6 | G7: 7 | H7: Former DEV-05 moved up one ID after the merge above; text unchanged.
A8: S1-DEV-05 | B8: Developer | C8: 1 | D8: Reset password: request, emailed token, reset form | E8: User Management screen: user list, Add User, Edit User, Block/Unblock; Admin manages Users only and Superadmin accounts are hidden | F8: 7 | G8: 8 | H8: NEW: the User Management module in the guide (3.8) had no PR. Uses the slot freed by the merge.
A9: S1-DEV-07 | B9: Developer | C9: 1 | D9: Admin/superadmin: assign per-module rights (view, edit, delete); log every rights change in audit_log | E9: Rights dialog: admin/superadmin assign per-action rights by module (Customer, Product, Human Resources, Sales, Reports) with module checkbox and All/None; log every rights change in audit_log | F9: 9 | G9: 9 | H9: Guide uses per-action rights (36), not only view/edit/delete per module.
A10: S1-DEV-08 | B10: Developer | C10: 1 | D10: Main page: module tiles by view right, plus server-side permission check | E10: Main page: sidebar and module tiles by role and rights, plus server-side permission check | F10: 9 | G10: 9 | H10: Menu now follows per-action rights and role, as in the guide dashboards.
A11: S1-DBA-03 | B11: DB Admin | C11: 1 | D11: Migration: app_user, role, module, user_permission (with soft delete) | E11: Migration: app_user (role, blocked flag), role, module, rights catalogue, user_permission (with soft delete) | F11: 4 | G11: 4 | H11: Needs a blocked flag and a per-action rights catalogue to support User Management.
A12: S1-DBA-05 | B12: DB Admin | C12: 1 | D12: Seed data: one superadmin account per team member, 4 modules, default roles (no passwords in the repo; first password set via one-time set-password link) | E12: Seed data: one superadmin account per team member, modules (Customer, Product, Human Resources, Sales, Reports), the per-action rights catalogue (36 rights, guide 3.8), default roles (no passwords in the repo; first password set via one-time set-password link) | F12: 5 | G12: 5 | H12: Seed matches the guide: five rights modules plus the 36-right catalogue (old text said 4 modules).
A13: S1-TST-02 | B13: Tester | C13: 1 | D13: Test cases: register and login | E13: Test cases: register, login and logout, set and reset password (expired and reused token) | F13: 5 | G13: 7 | H13: Merged old TST-02 + TST-03 to free one test slot.
A14: S1-TST-03 | B14: Tester | C14: 1 | D14: Test cases: set and reset password (expired and reused token) | E14: Test cases: User Management (add, edit, block/unblock, approve, designate admin; Admin cannot see or edit Superadmin; last-superadmin guard) | F14: 7 | G14: 8 | H14: NEW: tests for the User Management screen.
A15: S1-TST-04 | B15: Tester | C15: 1 | D15: Permission matrix tests (superadmin/admin/user x view/edit/delete), using registered and approved test accounts for admin and user | E15: Permission matrix tests (superadmin/admin/user x each right), using registered and approved test accounts; menu, buttons and server all follow the rights | F15: 9 | G15: 9 | H15: Per-action rights; checks the UI and the server agree (a hidden button is not enough).
A16: S1-UIX-03 | B16: UI/UX Designer | C16: 1 | D16: Wireframes: main page and user-rights management | E16: Wireframes: main page, User Management list and Rights dialog | F16: 4 | G16: 4 | H16: Adds the User Management list screen to the wireframes.
A17: S1-UIX-04 | B17: UI/UX Designer | C17: 1 | D17: Hi-fi mockups and developer handoff notes | E17: Hi-fi mockups (login, register, main page, User Management, Rights dialog) and developer handoff notes | F17: 6 | G17: 6 | H17: Mockups now cover User Management.
... A37: S4-TST-04 | B37: Tester | C37: 4 | D37: End-to-end test: register, approve, login, sell, pay | E37: End-to-end test: register, approve, assign rights, login, sell, pay, run reports | F37: 8 | G37: 8 | H37: Now includes User Management and Reports in the chain.
